{
  "updated": "2026-07-04T13:54:08Z",
  "daily": {
    "btc": {
      "pnl": 0.77,
      "trades": 71,
      "wins": 54,
      "wr": 76.1
    },
    "eth": {
      "pnl": -17.72,
      "trades": 86,
      "wins": 66,
      "wr": 76.7
    },
    "sol": {
      "pnl": -3.8,
      "trades": 1,
      "wins": 0,
      "wr": 0.0
    },
    "xrp": {
      "pnl": 0,
      "trades": 0,
      "wins": 0,
      "wr": 0
    },
    "total": {
      "pnl": -20.75,
      "trades": 158,
      "wins": 120,
      "wr": 75.9
    }
  },
  "history": [
    {
      "date": "2026-07-01",
      "pnl": -12.48,
      "trades": 31,
      "wins": 16,
      "wr": 51.6
    },
    {
      "date": "2026-07-02",
      "pnl": -4.72,
      "trades": 266,
      "wins": 211,
      "wr": 79.3
    },
    {
      "date": "2026-07-03",
      "pnl": -5.94,
      "trades": 243,
      "wins": 194,
      "wr": 79.8
    },
    {
      "date": "2026-07-04",
      "pnl": -24.75,
      "trades": 159,
      "wins": 120,
      "wr": 75.5
    }
  ]
}
