{
  "updated": "2026-07-02T22:52:02Z",
  "daily": {
    "btc": {
      "pnl": -23.09,
      "trades": 105,
      "wins": 82,
      "wr": 78.1
    },
    "eth": {
      "pnl": 53.92,
      "trades": 104,
      "wins": 92,
      "wr": 88.5
    },
    "sol": {
      "pnl": -28.95,
      "trades": 31,
      "wins": 19,
      "wr": 61.3
    },
    "xrp": {
      "pnl": -26.25,
      "trades": 17,
      "wins": 9,
      "wr": 52.9
    },
    "total": {
      "pnl": -24.37,
      "trades": 257,
      "wins": 202,
      "wr": 78.6
    }
  },
  "history": [
    {
      "date": "2026-06-29",
      "pnl": 60.94,
      "trades": 196,
      "wins": 119,
      "wr": 60.7
    },
    {
      "date": "2026-06-30",
      "pnl": 67.25,
      "trades": 69,
      "wins": 49,
      "wr": 71.0
    },
    {
      "date": "2026-07-01",
      "pnl": -12.48,
      "trades": 31,
      "wins": 16,
      "wr": 51.6
    },
    {
      "date": "2026-07-02",
      "pnl": -24.37,
      "trades": 257,
      "wins": 202,
      "wr": 78.6
    }
  ]
}
